jsd_job_bot/__init__.py
jsd_job_bot/__main__.py
jsd_job_bot-0.0.3.dist-info/entry_points.txt
jsd_job_bot-0.0.3.dist-info/WHEEL
jsd_job_bot-0.0.3.dist-info/METADATA
jsd_job_bot-0.0.3.dist-info/RECORD
