Metadata-Version: 2.1
Name: jsd-job-bot
Version: 0.0.3
Summary: Jira Service Desk job tracker.
Home-page: https://github.com/yaleman/jsd_job_bot
License: MIT
Author: James Hodgkinson
Author-email: james@terminaloutcomes.com
Requires-Python: >=3.9,<4.0
Classifier: Development Status :: 4 - Beta
Classifier: Intended Audience :: Developers
Classifier: License :: OSI Approved :: MIT License
Classifier: Programming Language :: Python :: 3
Classifier: Programming Language :: Python :: 3.10
Classifier: Programming Language :: Python :: 3.7
Classifier: Programming Language :: Python :: 3.8
Classifier: Programming Language :: Python :: 3.9
Classifier: Topic :: Internet :: WWW/HTTP :: Dynamic Content
Requires-Dist: jira (>=3.2.0,<4.0.0)
Requires-Dist: loguru (>=0.6.0,<0.7.0)
Requires-Dist: python-dateutil (>=2.8.2,<3.0.0)
Requires-Dist: texttable (>=1.6.4,<2.0.0)
Project-URL: Repository, https://github.com/yaleman/jsd_job_bot
